{
  "BB Owes": {
    "name": "BB Owes",
    "components": {
      "keywords": [
        "canyon"
      ],
      "transactions": []
    },
    "coins": 0
  },
  "Mortgage": {
    "name": "Mortgage",
    "components": {
      "keywords": [
        "cooper"
      ],
      "transactions": []
    },
    "coins": 2627,
    "depositCadence": {
      "type": "exact",
      "incidence": "bi-weekly",
      "amount": 1314,
      "importanceLevel": 1,
      "lastUpdated": 1726200000000
    },
    "group": "House"
  },
  "Utilities": {
    "name": "Utilities",
    "components": {
      "keywords": [
        "frontier",
        "fort wayne utili",
        "xcel",
        "aepindia",
        "celina",
        "nipsco"
      ],
      "transactions": []
    },
    "coins": 837,
    "depositCadence": {
      "type": "exact",
      "incidence": "bi-weekly",
      "amount": 419,
      "importanceLevel": 2,
      "lastUpdated": 1726200000000
    },
    "group": "House"
  },
  "Food": {
    "name": "Food",
    "components": {
      "keywords": [
        "safeway",
        "costco",
        "kroger",
        "wall-mart",
        "meijer",
        "aldi"
      ],
      "transactions": []
    },
    "coins": 750,
    "depositCadence": {
      "type": "exact",
      "incidence": "bi-weekly",
      "amount": 750,
      "importanceLevel": 3,
      "lastUpdated": 1726200000000
    },
    "group": "Family"
  },
  "Emergency Fund": {
    "name": "Emergency Fund",
    "components": {
      "keywords": [],
      "transactions": []
    },
    "coins": 27487,
    "depositCadence": {
      "type": "exact",
      "incidence": "bi-weekly",
      "amount": 1000,
      "importanceLevel": 4,
      "lastUpdated": 1726200000000
    },
    "group": "Emergency Fund"
  },
  "Subscriptions": {
    "name": "Subscriptions",
    "components": {
      "keywords": [
        "audible",
        "lee brothers",
        "spotify",
        "dropbox",
        "prime",
        "ring",
        "disney plus",
        "netflix",
        "lastpass"
      ],
      "transactions": []
    },
    "coins": 315,
    "depositCadence": {
      "type": "exact",
      "incidence": "bi-weekly",
      "amount": 158,
      "importanceLevel": 5,
      "lastUpdated": 1726200000000
    },
    "group": "House"
  },
  "Family Coin": {
    "name": "Family Coin",
    "components": {
      "keywords": [
        "amazon",
        "menards",
        "hicksville sport",
        "masters heating & cooling",
        "bargain lane",
        "chelsea kelly"
      ],
      "transactions": []
    },
    "coins": 3000,
    "depositCadence": {
      "type": "exact",
      "incidence": "bi-weekly",
      "amount": 300,
      "importanceLevel": 6,
      "lastUpdated": 1726200000000
    },
    "group": "Family"
  },
  "lastUpdated": 1726200000000
}
